{
    "name": "Agregar cliente al grupo de clientes",
    "url": "/billing.php/customerGroupsCustomers/",
    "description": "Módulo para agregar cliente al grupo de clientes",
    "task": {
        "key": "task.billing.customerGroupsCustomers.create",
        "name": "Acceso a agregar cliente al grupo de clientes",
        "description": "Permitir agregar cliente al grupo de clientes",
        "pattern": "create"
    },
    "event": {
        "key": "event.billing.customerGroupsCustomers.create.success",
        "description": "Cliente agregado a grupo de clientes"
    }
}